pyjapanglish/__init__.py
pyjapanglish/cmudict_jp.py
pyjapanglish/japanglish.py
pyjapanglish-1.0.dist-info/LICENSE
pyjapanglish-1.0.dist-info/LICENSE_cmudict
pyjapanglish-1.0.dist-info/METADATA
pyjapanglish-1.0.dist-info/WHEEL
pyjapanglish-1.0.dist-info/top_level.txt
pyjapanglish-1.0.dist-info/RECORD
