Metadata-Version: 2.1
Name: pyjapanglish
Version: 1.0
Summary: 英単語をひらがなでの読みに変換する。詳しくはHomepage(Github)をご覧ください。
Author: Nanahuse
License: MIT License
Project-URL: Homepage, https://github.com/Nanahuse/PyJapanglish
Classifier: License :: OSI Approved :: MIT License
Classifier: Programming Language :: Python :: 3.10
Classifier: Programming Language :: Python :: 3.11
Requires-Python: >=3.10
License-File: LICENSE
License-File: LICENSE_cmudict
Requires-Dist: pyphonixjp >=1.2
